{
  "code": "799",
  "nameEs": "Urano",
  "data": {
    "planet": "Uranus",
    "count": 22,
    "items": [
      {
        "title": "Uranus",
        "nasaId": "PIA01391",
        "url": "https://images-assets.nasa.gov/image/PIA01391/PIA01391~small.jpg",
        "source": "images-api.nasa.gov",
        "keywords": [
          "uranus",
          "voyager"
        ]
      },
      {
        "title": "GIF of Uranus' Magnetic Field",
        "nasaId": "PIA23683",
        "url": "https://images-assets.nasa.gov/image/PIA23683/PIA23683~thumb.jpg",
        "source": "images-api.nasa.gov",
        "keywords": [
          "voyager",
          "uranus"
        ]
      },
      {
        "title": "Uranus Atmosphere",
        "nasaId": "PIA01535",
        "url": "https://images-assets.nasa.gov/image/PIA01535/PIA01535~small.jpg",
        "source": "images-api.nasa.gov",
        "keywords": [
          "uranus",
          "voyager"
        ]
      },
      {
        "title": "Uranus - Final Image",
        "nasaId": "PIA00143",
        "url": "https://images-assets.nasa.gov/image/PIA00143/PIA00143~small.jpg",
        "source": "images-api.nasa.gov",
        "keywords": [
          "uranus",
          "voyager"
        ]
      },
      {
        "title": "Uranus Atmosphere",
        "nasaId": "PIA01489",
        "url": "https://images-assets.nasa.gov/image/PIA01489/PIA01489~small.jpg",
        "source": "images-api.nasa.gov",
        "keywords": [
          "uranus",
          "voyager"
        ]
      },
      {
        "title": "Uranus as seen by NASA Voyager 2",
        "nasaId": "PIA18182",
        "url": "https://images-assets.nasa.gov/image/PIA18182/PIA18182~medium.jpg",
        "source": "images-api.nasa.gov",
        "keywords": [
          "uranus",
          "voyager"
        ]
      },
      {
        "title": "Color Voyager 2 Image Showing Crescent Uranus",
        "nasaId": "PIA00346",
        "url": "https://images-assets.nasa.gov/image/PIA00346/PIA00346~thumb.jpg",
        "source": "images-api.nasa.gov",
        "keywords": [
          "uranus",
          "voyager"
        ]
      },
      {
        "title": "Uranus Upper Atmosphere",
        "nasaId": "PIA01488",
        "url": "https://images-assets.nasa.gov/image/PIA01488/PIA01488~medium.jpg",
        "source": "images-api.nasa.gov",
        "keywords": [
          "uranus",
          "voyager"
        ]
      },
      {
        "title": "Uranus in True and False Color",
        "nasaId": "PIA00032",
        "url": "https://images-assets.nasa.gov/image/PIA00032/PIA00032~small.jpg",
        "source": "images-api.nasa.gov",
        "keywords": [
          "uranus",
          "voyager"
        ]
      },
      {
        "title": "Uranus - Discrete Cloud",
        "nasaId": "PIA00370",
        "url": "https://images-assets.nasa.gov/image/PIA00370/PIA00370~small.jpg",
        "source": "images-api.nasa.gov",
        "keywords": [
          "uranus",
          "voyager"
        ]
      },
      {
        "title": "Hubble Captures Detailed Image of Uranus Atmosphere",
        "nasaId": "PIA01280",
        "url": "https://images-assets.nasa.gov/image/PIA01280/PIA01280~thumb.jpg",
        "source": "images-api.nasa.gov",
        "keywords": [
          "uranus",
          "hubble space telescope"
        ]
      },
      {
        "title": "Uranus Cloud Movement",
        "nasaId": "PIA00369",
        "url": "https://images-assets.nasa.gov/image/PIA00369/PIA00369~thumb.jpg",
        "source": "images-api.nasa.gov",
        "keywords": [
          "uranus",
          "voyager"
        ]
      },
      {
        "title": "Hubble Observes the Planet Uranus",
        "nasaId": "PIA01282",
        "url": "https://images-assets.nasa.gov/image/PIA01282/PIA01282~thumb.jpg",
        "source": "images-api.nasa.gov",
        "keywords": [
          "uranus",
          "hubble space telescope"
        ]
      },
      {
        "title": "Hubble Observes the Moons and Rings of Uranus",
        "nasaId": "PIA01281",
        "url": "https://images-assets.nasa.gov/image/PIA01281/PIA01281~thumb.jpg",
        "source": "images-api.nasa.gov",
        "keywords": [
          "uranus",
          "hubble space telescope"
        ]
      },
      {
        "title": "Hubble Tracks Clouds on Uranus",
        "nasaId": "PIA01278",
        "url": "https://images-assets.nasa.gov/image/PIA01278/PIA01278~small.jpg",
        "source": "images-api.nasa.gov",
        "keywords": [
          "uranus",
          "hubble space telescope"
        ]
      },
      {
        "title": "Hubble the Rotation of Uranus",
        "nasaId": "PIA01283",
        "url": "https://images-assets.nasa.gov/image/PIA01283/PIA01283~thumb.jpg",
        "source": "images-api.nasa.gov",
        "keywords": [
          "uranus",
          "hubble space telescope"
        ]
      },
      {
        "title": "Major Moons of Uranus",
        "nasaId": "PIA25500",
        "url": "https://images-assets.nasa.gov/image/PIA25500/PIA25500~small.jpg",
        "source": "images-api.nasa.gov",
        "keywords": [
          "voyager",
          "uranus"
        ]
      },
      {
        "title": "Hubble Spots Northern Hemispheric Clouds on Uranus",
        "nasaId": "PIA01279",
        "url": "https://images-assets.nasa.gov/image/PIA01279/PIA01279~small.jpg",
        "source": "images-api.nasa.gov",
        "keywords": [
          "uranus",
          "hubble space telescope"
        ]
      },
      {
        "title": "Uranus, Toward the Planet Pole of Rotation",
        "nasaId": "PIA01360",
        "url": "https://images-assets.nasa.gov/image/PIA01360/PIA01360~small.jpg",
        "source": "images-api.nasa.gov",
        "keywords": [
          "uranus",
          "voyager"
        ]
      },
      {
        "title": "Hubble Finds Many Bright Clouds on Uranus",
        "nasaId": "PIA02963",
        "url": "https://images-assets.nasa.gov/image/PIA02963/PIA02963~medium.jpg",
        "source": "images-api.nasa.gov",
        "keywords": [
          "uranus",
          "hubble space telescope"
        ]
      },
      {
        "title": "Hubble Reveals Dynamic Atmospheres of Uranus, Neptune",
        "nasaId": "stsci-h-p1906c-f-514x514.a",
        "url": "https://images-assets.nasa.gov/image/stsci-h-p1906c-f-514x514.a/stsci-h-p1906c-f-514x514.a~thumb.jpg",
        "source": "images-api.nasa.gov",
        "keywords": [
          "uranus",
          "neptune"
        ]
      },
      {
        "title": "Hubble Reveals Dynamic Atmospheres of Uranus, Neptune",
        "nasaId": "stsci-h-p1906a-f-1028x543",
        "url": "https://images-assets.nasa.gov/image/stsci-h-p1906a-f-1028x543/stsci-h-p1906a-f-1028x543~thumb.jpg",
        "source": "images-api.nasa.gov",
        "keywords": [
          "uranus",
          "neptune",
          "hubble",
          "nasa goddard"
        ]
      }
    ]
  }
}